{
  "nodes": [
    {
      "id": "Robert E. Gates",
      "type": "Person",
      "properties": {}
    },
    {
      "id": "Altoona",
      "type": "Location",
      "properties": {}
    },
    {
      "id": "Massachusetts",
      "type": "Location",
      "properties": {}
    },
    {
      "id": "Patricia Gates",
      "type": "Person",
      "properties": {}
    },
    {
      "id": "Cindy Thompson",
      "type": "Person",
      "properties": {}
    },
    {
      "id": "Heather Cramer",
      "type": "Person",
      "properties": {}
    },
    {
      "id": "Laramy",
      "type": "Person",
      "properties": {}
    },
    {
      "id": "Jessica Gates",
      "type": "Person",
      "properties": {}
    },
    {
      "id": "Cheryl Mckeen",
      "type": "Person",
      "properties": {}
    },
    {
      "id": "Florida",
      "type": "Location",
      "properties": {}
    },
    {
      "id": "Carol Martin",
      "type": "Person",
      "properties": {}
    },
    {
      "id": "Indiana",
      "type": "Location",
      "properties": {}
    },
    {
      "id": "Joan Thompson",
      "type": "Person",
      "properties": {}
    },
    {
      "id": "Sandy Steve Martin",
      "type": "Person",
      "properties": {}
    },
    {
      "id": "Tennessee",
      "type": "Location",
      "properties": {}
    },
    {
      "id": "Anna Cramer",
      "type": "Person",
      "properties": {}
    },
    {
      "id": "Us Marine Corps",
      "type": "Organization",
      "properties": {}
    },
    {
      "id": "Altoona Hospital",
      "type": "Organization",
      "properties": {}
    },
    {
      "id": "Williamsburg Police Department",
      "type": "Organization",
      "properties": {}
    },
    {
      "id": "Wehnwood United Wesleyan Church",
      "type": "Organization",
      "properties": {}
    }
  ],
  "relationships": [
    {
      "source": {
        "id": "Robert E. Gates",
        "type": "Person",
        "properties": {}
      },
      "target": {
        "id": "Altoona",
        "type": "Location",
        "properties": {}
      },
      "type": "LIVED_IN",
      "properties": {}
    },
    {
      "source": {
        "id": "Robert E. Gates",
        "type": "Person",
        "properties": {}
      },
      "target": {
        "id": "Massachusetts",
        "type": "Location",
        "properties": {}
      },
      "type": "BORN_IN",
      "properties": {}
    },
    {
      "source": {
        "id": "Robert E. Gates",
        "type": "Person",
        "properties": {}
      },
      "target": {
        "id": "Patricia Gates",
        "type": "Person",
        "properties": {}
      },
      "type": "PARENT_OF",
      "properties": {}
    },
    {
      "source": {
        "id": "Robert E. Gates",
        "type": "Person",
        "properties": {}
      },
      "target": {
        "id": "Cindy Thompson",
        "type": "Person",
        "properties": {}
      },
      "type": "MARRIED_TO",
      "properties": {}
    },
    {
      "source": {
        "id": "Robert E. Gates",
        "type": "Person",
        "properties": {}
      },
      "target": {
        "id": "Heather Cramer",
        "type": "Person",
        "properties": {}
      },
      "type": "PARENT_OF",
      "properties": {}
    },
    {
      "source": {
        "id": "Robert E. Gates",
        "type": "Person",
        "properties": {}
      },
      "target": {
        "id": "Jessica Gates",
        "type": "Person",
        "properties": {}
      },
      "type": "PARENT_OF",
      "properties": {}
    },
    {
      "source": {
        "id": "Robert E. Gates",
        "type": "Person",
        "properties": {}
      },
      "target": {
        "id": "Cheryl Mckeen",
        "type": "Person",
        "properties": {}
      },
      "type": "SIBLING_OF",
      "properties": {}
    },
    {
      "source": {
        "id": "Robert E. Gates",
        "type": "Person",
        "properties": {}
      },
      "target": {
        "id": "Carol Martin",
        "type": "Person",
        "properties": {}
      },
      "type": "SIBLING_OF",
      "properties": {}
    },
    {
      "source": {
        "id": "Robert E. Gates",
        "type": "Person",
        "properties": {}
      },
      "target": {
        "id": "Joan Thompson",
        "type": "Person",
        "properties": {}
      },
      "type": "MOTHER-IN-LAW_OF",
      "properties": {}
    },
    {
      "source": {
        "id": "Robert E. Gates",
        "type": "Person",
        "properties": {}
      },
      "target": {
        "id": "Sandy Steve Martin",
        "type": "Person",
        "properties": {}
      },
      "type": "AUNT_OF",
      "properties": {}
    },
    {
      "source": {
        "id": "Robert E. Gates",
        "type": "Person",
        "properties": {}
      },
      "target": {
        "id": "Tennessee",
        "type": "Location",
        "properties": {}
      },
      "type": "RELATIVE_IN",
      "properties": {}
    },
    {
      "source": {
        "id": "Robert E. Gates",
        "type": "Person",
        "properties": {}
      },
      "target": {
        "id": "Anna Cramer",
        "type": "Person",
        "properties": {}
      },
      "type": "GRANDPARENT_OF",
      "properties": {}
    },
    {
      "source": {
        "id": "Robert E. Gates",
        "type": "Person",
        "properties": {}
      },
      "target": {
        "id": "Us Marine Corps",
        "type": "Organization",
        "properties": {}
      },
      "type": "SERVED_IN",
      "properties": {}
    },
    {
      "source": {
        "id": "Robert E. Gates",
        "type": "Person",
        "properties": {}
      },
      "target": {
        "id": "Altoona Hospital",
        "type": "Organization",
        "properties": {}
      },
      "type": "WORKED_AT",
      "properties": {}
    },
    {
      "source": {
        "id": "Robert E. Gates",
        "type": "Person",
        "properties": {}
      },
      "target": {
        "id": "Williamsburg Police Department",
        "type": "Organization",
        "properties": {}
      },
      "type": "WORKED_AT",
      "properties": {}
    },
    {
      "source": {
        "id": "Robert E. Gates",
        "type": "Person",
        "properties": {}
      },
      "target": {
        "id": "Wehnwood United Wesleyan Church",
        "type": "Organization",
        "properties": {}
      },
      "type": "MEMBER_OF",
      "properties": {}
    }
  ]
}