{
  "nodes": [
    {
      "id": "Einstein",
      "type": "Person",
      "properties": {}
    },
    {
      "id": "Podolsky",
      "type": "Person",
      "properties": {}
    },
    {
      "id": "Rosen",
      "type": "Person",
      "properties": {}
    },
    {
      "id": "Schrodinger",
      "type": "Person",
      "properties": {}
    },
    {
      "id": "Alice",
      "type": "Person",
      "properties": {}
    },
    {
      "id": "Bob",
      "type": "Person",
      "properties": {}
    },
    {
      "id": "David Jennings",
      "type": "Person",
      "properties": {}
    }
  ],
  "relationships": [
    {
      "source": {
        "id": "Einstein",
        "type": "Person",
        "properties": {}
      },
      "target": {
        "id": "Podolsky",
        "type": "Person",
        "properties": {}
      },
      "type": "COLLABORATED",
      "properties": {}
    },
    {
      "source": {
        "id": "Podolsky",
        "type": "Person",
        "properties": {}
      },
      "target": {
        "id": "Rosen",
        "type": "Person",
        "properties": {}
      },
      "type": "COLLABORATED",
      "properties": {}
    },
    {
      "source": {
        "id": "Schrodinger",
        "type": "Person",
        "properties": {}
      },
      "target": {
        "id": "Einstein",
        "type": "Person",
        "properties": {}
      },
      "type": "COINED_TERM",
      "properties": {}
    },
    {
      "source": {
        "id": "Alice",
        "type": "Person",
        "properties": {}
      },
      "target": {
        "id": "Bob",
        "type": "Person",
        "properties": {}
      },
      "type": "MEASUREMENT_PARTNERS",
      "properties": {}
    },
    {
      "source": {
        "id": "David Jennings",
        "type": "Person",
        "properties": {}
      },
      "target": {
        "id": "This Work",
        "type": "Work",
        "properties": {}
      },
      "type": "CONTRIBUTED_TO",
      "properties": {}
    },
    {
      "source": {
        "id": "David Jennings",
        "type": "Person",
        "properties": {}
      },
      "target": {
        "id": "One",
        "type": "Function",
        "properties": {}
      },
      "type": "DERIVED_FROM",
      "properties": {}
    },
    {
      "source": {
        "id": "One",
        "type": "Function",
        "properties": {}
      },
      "target": {
        "id": "Xmath159",
        "type": "Function",
        "properties": {}
      },
      "type": "DERIVED_FROM",
      "properties": {}
    },
    {
      "source": {
        "id": "One",
        "type": "Function",
        "properties": {}
      },
      "target": {
        "id": "Xmath160",
        "type": "Vector",
        "properties": {}
      },
      "type": "UNIT_VECTOR",
      "properties": {}
    },
    {
      "source": {
        "id": "Xmath157",
        "type": "Vector",
        "properties": {}
      },
      "target": {
        "id": "Xmath80",
        "type": "Vector",
        "properties": {}
      },
      "type": "UNIT_VECTOR",
      "properties": {}
    },
    {
      "source": {
        "id": "Xmath157",
        "type": "Vector",
        "properties": {}
      },
      "target": {
        "id": "Xmath168",
        "type": "Vector",
        "properties": {}
      },
      "type": "UNIT_VECTOR",
      "properties": {}
    },
    {
      "source": {
        "id": "Xmath157",
        "type": "Vector",
        "properties": {}
      },
      "target": {
        "id": "Xmath174",
        "type": "Vector",
        "properties": {}
      },
      "type": "UNIT_VECTOR",
      "properties": {}
    },
    {
      "source": {
        "id": "Xmath168",
        "type": "Vector",
        "properties": {}
      },
      "target": {
        "id": "Xmath174",
        "type": "Vector",
        "properties": {}
      },
      "type": "SUBDIVIDED_TO",
      "properties": {}
    },
    {
      "source": {
        "id": "Xmath174",
        "type": "Vector",
        "properties": {}
      },
      "target": {
        "id": "Xmath174",
        "type": "Vector",
        "properties": {}
      },
      "type": "SUBDIVIDED_TO",
      "properties": {}
    },
    {
      "source": {
        "id": "Xmath174",
        "type": "Vector",
        "properties": {}
      },
      "target": {
        "id": "Orthogonal Operator",
        "type": "Operator",
        "properties": {}
      },
      "type": "ADDED",
      "properties": {}
    },
    {
      "source": {
        "id": "Orthogonal Operator",
        "type": "Operator",
        "properties": {}
      },
      "target": {
        "id": "Xmath167",
        "type": "Vector",
        "properties": {}
      },
      "type": "ROTATES_TO",
      "properties": {}
    },
    {
      "source": {
        "id": "Xmath167",
        "type": "Vector",
        "properties": {}
      },
      "target": {
        "id": "Xmath177",
        "type": "Vector",
        "properties": {}
      },
      "type": "ROTATES_TO",
      "properties": {}
    },
    {
      "source": {
        "id": "Xmath177",
        "type": "Vector",
        "properties": {}
      },
      "target": {
        "id": "Xmath178",
        "type": "Value",
        "properties": {}
      },
      "type": "ROTATES_TO",
      "properties": {}
    },
    {
      "source": {
        "id": "Xmath179",
        "type": "Value",
        "properties": {}
      },
      "target": {
        "id": "Xmath180",
        "type": "Curve",
        "properties": {}
      },
      "type": "VARYING_FROM_TO",
      "properties": {}
    },
    {
      "source": {
        "id": "Xmath179",
        "type": "Value",
        "properties": {}
      },
      "target": {
        "id": "Xmath183",
        "type": "Value",
        "properties": {}
      },
      "type": "VARYING_FROM_TO",
      "properties": {}
    },
    {
      "source": {
        "id": "Xmath184",
        "type": "Value",
        "properties": {}
      },
      "target": {
        "id": "Xmath184",
        "type": "Value",
        "properties": {}
      },
      "type": "VARYING_FROM_TO",
      "properties": {}
    },
    {
      "source": {
        "id": "Xmath184",
        "type": "Value",
        "properties": {}
      },
      "target": {
        "id": "Xmath184",
        "type": "Value",
        "properties": {}
      },
      "type": "VARYING_FROM_TO",
      "properties": {}
    },
    {
      "source": {
        "id": "Xmath184",
        "type": "Value",
        "properties": {}
      },
      "target": {
        "id": "Xmath185",
        "type": "Curve",
        "properties": {}
      },
      "type": "VARYING_TO",
      "properties": {}
    },
    {
      "source": {
        "id": "Xmath199",
        "type": "Surface integral",
        "properties": {}
      },
      "target": {
        "id": "Eq. (Qv)",
        "type": "Equation",
        "properties": {}
      },
      "type": "WRITTEN_IN",
      "properties": {}
    },
    {
      "source": {
        "id": "Eq. (Qv)",
        "type": "Equation",
        "properties": {}
      },
      "target": {
        "id": "Xmath200",
        "type": "Value",
        "properties": {}
      },
      "type": "WRITTEN_IN",
      "properties": {}
    },
    {
      "source": {
        "id": "Xmath222",
        "type": "Value",
        "properties": {}
      },
      "target": {
        "id": "1/2",
        "type": "Value",
        "properties": {}
      },
      "type": "RIGHT_IN",
      "properties": {}
    },
    {
      "source": {
        "id": "Xmath184",
        "type": "Value",
        "properties": {}
      },
      "target": {
        "id": "Xmath199",
        "type": "Surface integral",
        "properties": {}
      },
      "type": "INTEGRATED_OVER",
      "properties": {}
    },
    {
      "source": {
        "id": "Xmath184",
        "type": "Value",
        "properties": {}
      },
      "target": {
        "id": "Xmath199",
        "type": "Surface integral",
        "properties": {}
      },
      "type": "INTEGRATED_OVER",
      "properties": {}
    },
    {
      "source": {
        "id": "Xmath217",
        "type": "Parameter",
        "properties": {}
      },
      "target": {
        "id": "Xmath218",
        "type": "Parameter",
        "properties": {}
      },
      "type": "DIFFERENTIATED_WITH_RESPECT_TO",
      "properties": {}
    },
    {
      "source": {
        "id": "Xmath217",
        "type": "Parameter",
        "properties": {}
      },
      "target": {
        "id": "Xmath218",
        "type": "Parameter",
        "properties": {}
      },
      "type": "DIFFERENTIATED_WITH_RESPECT_TO",
      "properties": {}
    },
    {
      "source": {
        "id": "Pi",
        "type": "Value",
        "properties": {}
      },
      "target": {
        "id": "Cos 2 Alpha",
        "type": "Value",
        "properties": {}
      },
      "type": "INTEGRATED_OVER",
      "properties": {}
    },
    {
      "source": {
        "id": "M Cos Beta - N Sin Beta",
        "type": "Value",
        "properties": {}
      },
      "target": {
        "id": "P225",
        "type": "Case",
        "properties": {}
      },
      "type": "CHOSEN",
      "properties": {}
    },
    {
      "source": {
        "id": "P225",
        "type": "Case",
        "properties": {}
      },
      "target": {
        "id": "Lhs-Model",
        "type": "Model",
        "properties": {}
      },
      "type": "HAS",
      "properties": {}
    },
    {
      "source": {
        "id": "P225",
        "type": "Case",
        "properties": {}
      },
      "target": {
        "id": "Eq. ([Lhs-])",
        "type": "Equation",
        "properties": {}
      },
      "type": "DISTINGUISHED",
      "properties": {}
    },
    {
      "source": {
        "id": "P225",
        "type": "Case",
        "properties": {}
      },
      "target": {
        "id": "Covariance Function",
        "type": "Function",
        "properties": {}
      },
      "type": "DISTINGUISHED",
      "properties": {}
    },
    {
      "source": {
        "id": "P5",
        "type": "Hidden state",
        "properties": {}
      },
      "target": {
        "id": "P5 X5",
        "type": "Converging state",
        "properties": {}
      },
      "type": "HAS",
      "properties": {}
    },
    {
      "source": {
        "id": "P5",
        "type": "Hidden state",
        "properties": {}
      },
      "target": {
        "id": "P5 (P5)",
        "type": "Converging state",
        "properties": {}
      },
      "type": "HAS",
      "properties": {}
    },
    {
      "source": {
        "id": "P5",
        "type": "Hidden state",
        "properties": {}
      },
      "target": {
        "id": "P5 (P5)",
        "type": "Converging state",
        "properties": {}
      },
      "type": "HAS",
      "properties": {}
    },
    {
      "source": {
        "id": "P5",
        "type": "Hidden state",
        "properties": {}
      },
      "target": {
        "id": "P5 5 (Lin)",
        "type": "Linear epr-steering inequality",
        "properties": {}
      },
      "type": "SHOWN",
      "properties": {}
    },
    {
      "source": {
        "id": "A Alpha Boldsymbol V",
        "type": "Value",
        "properties": {}
      },
      "target": {
        "id": "Boldsymbol B Cdot Boldsymbol V",
        "type": "Value",
        "properties": {}
      },
      "type": "DRAWN_USING",
      "properties": {}
    },
    {
      "source": {
        "id": "Boldsymbol B Cdot Boldsymbol V",
        "type": "Value",
        "properties": {}
      },
      "target": {
        "id": "Schwarz Inequality",
        "type": "Inequality",
        "properties": {}
      },
      "type": "DRAWN_USING",
      "properties": {}
    },
    {
      "source": {
        "id": "Xmath271",
        "type": "Value",
        "properties": {}
      },
      "target": {
        "id": "2/3",
        "type": "Value",
        "properties": {}
      },
      "type": "DRAWN_USING",
      "properties": {}
    }
  ]
}