{
  "nodes": [
    {
      "id": "Goal",
      "type": "Concept",
      "properties": {}
    },
    {
      "id": "Physical Exertion Routine",
      "type": "Activity",
      "properties": {}
    },
    {
      "id": "Weight Loss",
      "type": "Goal",
      "properties": {}
    },
    {
      "id": "Business",
      "type": "Goal",
      "properties": {}
    },
    {
      "id": "Community",
      "type": "Concept",
      "properties": {}
    },
    {
      "id": "Derek Sivers",
      "type": "Person",
      "properties": {}
    },
    {
      "id": "Researcher",
      "type": "Person",
      "properties": {}
    },
    {
      "id": "Social Acknowledgment",
      "type": "Concept",
      "properties": {}
    },
    {
      "id": "5K Race",
      "type": "Activity",
      "properties": {}
    },
    {
      "id": "Encouragement",
      "type": "Concept",
      "properties": {}
    },
    {
      "id": "Warm Feelings",
      "type": "Concept",
      "properties": {}
    },
    {
      "id": "Completeness",
      "type": "Concept",
      "properties": {}
    },
    {
      "id": "Personality",
      "type": "Concept",
      "properties": {}
    },
    {
      "id": "New Job",
      "type": "Goal",
      "properties": {}
    },
    {
      "id": "Professional Network",
      "type": "Concept",
      "properties": {}
    },
    {
      "id": "Business Opportunities",
      "type": "Concept",
      "properties": {}
    },
    {
      "id": "Letters Of Recommendation",
      "type": "Concept",
      "properties": {}
    },
    {
      "id": "Book",
      "type": "Goal",
      "properties": {}
    },
    {
      "id": "Writing",
      "type": "Activity",
      "properties": {}
    },
    {
      "id": "Success",
      "type": "Concept",
      "properties": {}
    },
    {
      "id": "Articles",
      "type": "Activity",
      "properties": {}
    },
    {
      "id": "Publication",
      "type": "Activity",
      "properties": {}
    },
    {
      "id": "Winter Holiday Break",
      "type": "Event",
      "properties": {}
    },
    {
      "id": "Winter Virus",
      "type": "Concept",
      "properties": {}
    }
  ],
  "relationships": [
    {
      "source": {
        "id": "Goal",
        "type": "Concept",
        "properties": {}
      },
      "target": {
        "id": "Physical Exertion Routine",
        "type": "Activity",
        "properties": {}
      },
      "type": "INVOLVES",
      "properties": {}
    },
    {
      "source": {
        "id": "Goal",
        "type": "Concept",
        "properties": {}
      },
      "target": {
        "id": "Weight Loss",
        "type": "Goal",
        "properties": {}
      },
      "type": "INVOLVES",
      "properties": {}
    },
    {
      "source": {
        "id": "Goal",
        "type": "Concept",
        "properties": {}
      },
      "target": {
        "id": "Business",
        "type": "Goal",
        "properties": {}
      },
      "type": "INVOLVES",
      "properties": {}
    },
    {
      "source": {
        "id": "Goal",
        "type": "Concept",
        "properties": {}
      },
      "target": {
        "id": "Community",
        "type": "Concept",
        "properties": {}
      },
      "type": "INVOLVES",
      "properties": {}
    },
    {
      "source": {
        "id": "Derek Sivers",
        "type": "Person",
        "properties": {}
      },
      "target": {
        "id": "Researcher",
        "type": "Person",
        "properties": {}
      },
      "type": "COLLABORATES_WITH",
      "properties": {}
    },
    {
      "source": {
        "id": "Researcher",
        "type": "Person",
        "properties": {}
      },
      "target": {
        "id": "Social Acknowledgment",
        "type": "Concept",
        "properties": {}
      },
      "type": "STUDIES",
      "properties": {}
    },
    {
      "source": {
        "id": "Goal",
        "type": "Concept",
        "properties": {}
      },
      "target": {
        "id": "5K Race",
        "type": "Activity",
        "properties": {}
      },
      "type": "INVOLVES",
      "properties": {}
    },
    {
      "source": {
        "id": "Goal",
        "type": "Concept",
        "properties": {}
      },
      "target": {
        "id": "Encouragement",
        "type": "Concept",
        "properties": {}
      },
      "type": "INVOLVES",
      "properties": {}
    },
    {
      "source": {
        "id": "Goal",
        "type": "Concept",
        "properties": {}
      },
      "target": {
        "id": "Warm Feelings",
        "type": "Concept",
        "properties": {}
      },
      "type": "INVOLVES",
      "properties": {}
    },
    {
      "source": {
        "id": "Warm Feelings",
        "type": "Concept",
        "properties": {}
      },
      "target": {
        "id": "Completeness",
        "type": "Concept",
        "properties": {}
      },
      "type": "LEADS_TO",
      "properties": {}
    },
    {
      "source": {
        "id": "Personality",
        "type": "Concept",
        "properties": {}
      },
      "target": {
        "id": "Goal",
        "type": "Concept",
        "properties": {}
      },
      "type": "INFLUENCES",
      "properties": {}
    },
    {
      "source": {
        "id": "Goal",
        "type": "Concept",
        "properties": {}
      },
      "target": {
        "id": "New Job",
        "type": "Goal",
        "properties": {}
      },
      "type": "INVOLVES",
      "properties": {}
    },
    {
      "source": {
        "id": "New Job",
        "type": "Goal",
        "properties": {}
      },
      "target": {
        "id": "Professional Network",
        "type": "Concept",
        "properties": {}
      },
      "type": "UTILIZES",
      "properties": {}
    },
    {
      "source": {
        "id": "Professional Network",
        "type": "Concept",
        "properties": {}
      },
      "target": {
        "id": "Business Opportunities",
        "type": "Concept",
        "properties": {}
      },
      "type": "PROVIDES",
      "properties": {}
    },
    {
      "source": {
        "id": "Professional Network",
        "type": "Concept",
        "properties": {}
      },
      "target": {
        "id": "Letters Of Recommendation",
        "type": "Concept",
        "properties": {}
      },
      "type": "PROVIDES",
      "properties": {}
    },
    {
      "source": {
        "id": "Goal",
        "type": "Concept",
        "properties": {}
      },
      "target": {
        "id": "Book",
        "type": "Goal",
        "properties": {}
      },
      "type": "INVOLVES",
      "properties": {}
    },
    {
      "source": {
        "id": "Goal",
        "type": "Concept",
        "properties": {}
      },
      "target": {
        "id": "Writing",
        "type": "Activity",
        "properties": {}
      },
      "type": "INVOLVES",
      "properties": {}
    },
    {
      "source": {
        "id": "Goal",
        "type": "Concept",
        "properties": {}
      },
      "target": {
        "id": "Success",
        "type": "Concept",
        "properties": {}
      },
      "type": "INVOLVES",
      "properties": {}
    },
    {
      "source": {
        "id": "Goal",
        "type": "Concept",
        "properties": {}
      },
      "target": {
        "id": "Articles",
        "type": "Activity",
        "properties": {}
      },
      "type": "INVOLVES",
      "properties": {}
    },
    {
      "source": {
        "id": "Articles",
        "type": "Activity",
        "properties": {}
      },
      "target": {
        "id": "Publication",
        "type": "Activity",
        "properties": {}
      },
      "type": "LEADS_TO",
      "properties": {}
    },
    {
      "source": {
        "id": "Goal",
        "type": "Concept",
        "properties": {}
      },
      "target": {
        "id": "Winter Holiday Break",
        "type": "Event",
        "properties": {}
      },
      "type": "INVOLVES",
      "properties": {}
    },
    {
      "source": {
        "id": "Winter Holiday Break",
        "type": "Event",
        "properties": {}
      },
      "target": {
        "id": "Winter Virus",
        "type": "Concept",
        "properties": {}
      },
      "type": "LEADS_TO",
      "properties": {}
    }
  ]
}